nightline/__init__.py
nightline/types.py
nightline/services/README.md
nightline/services/__init__.py
nightline/services/core.py
nightline/services/sqs.py
nightline-0.3.0.dist-info/METADATA
nightline-0.3.0.dist-info/WHEEL
nightline-0.3.0.dist-info/licenses/LICENSE
nightline-0.3.0.dist-info/RECORD
