Metadata-Version: 2.4
Name: nightline
Version: 0.3.0
Summary: Nightline is a modern Event Listening framework based on Pydantic.
License-File: LICENSE
Requires-Python: >=3.10
Requires-Dist: pydantic>=2.10.3
Requires-Dist: structlog>=24.4.0
Provides-Extra: pubsub
Requires-Dist: google-cloud-pubsub; extra == 'pubsub'
Provides-Extra: sqs
Requires-Dist: boto3; extra == 'sqs'
